russian_uncensor/__init__.py
russian_uncensor/n_grams.py
russian_uncensor/rd_wr_util.py
russian_uncensor/uncensored.py
russian_uncensor-0.0.2.dist-info/LICENSE
russian_uncensor-0.0.2.dist-info/METADATA
russian_uncensor-0.0.2.dist-info/WHEEL
russian_uncensor-0.0.2.dist-info/top_level.txt
russian_uncensor-0.0.2.dist-info/RECORD
